kmiac_backend_bot_shared/__init__.py
kmiac_backend_bot_shared/dto.py
kmiac_backend_bot_shared/enums.py
kmiac_backend_bot_shared-0.1.2.dist-info/METADATA
kmiac_backend_bot_shared-0.1.2.dist-info/WHEEL
kmiac_backend_bot_shared-0.1.2.dist-info/RECORD
