Metadata-Version: 2.3
Name: kmiac-backend-bot-shared
Version: 0.1.2
Summary: 
Author: pasha_danilevich
Author-email: danilevitch.pasha@yandex.ru
Requires-Python: >=3.11,<4.0
Classifier: Programming Language :: Python :: 3
Classifier: Programming Language :: Python :: 3.11
Classifier: Programming Language :: Python :: 3.12
Classifier: Programming Language :: Python :: 3.13
Requires-Dist: pydantic (>=2.11.7,<3.0.0)
